gameplay.py
leaderboard.csv
leaderboard.py
numberguess.py
setup.py
bin/numberguess
p_stone_labs/__init__.py
p_stone_labs.egg-info/PKG-INFO
p_stone_labs.egg-info/SOURCES.txt
p_stone_labs.egg-info/dependency_links.txt
p_stone_labs.egg-info/not-zip-safe
p_stone_labs.egg-info/top_level.txt