Metadata-Version: 1.0
Name: p-stone-labs
Version: 0.32
Summary: P-Stone Labs
Home-page: http://github.com/gravitt8460
Author: P-Stone
Author-email: max.gravitt@gmail.com
License: MIT
Platform: UNKNOWN
